{
  "recentFiles": [
    {
      "basename": "3 Układ komponentów",
      "path": "C Sharp/C Sharp od Podstaw do WPF i XAML/3 Układ komponentów.md"
    },
    {
      "basename": "2 Aplikacje WPF",
      "path": "C Sharp/C Sharp od Podstaw do WPF i XAML/2 Aplikacje WPF.md"
    },
    {
      "basename": "1 OOP w CSharp",
      "path": "C Sharp/C Sharp od Podstaw do WPF i XAML/1 OOP w CSharp.md"
    },
    {
      "basename": "4 Tworzenie aplikacji WPF",
      "path": "C Sharp/C Sharp od Podstaw do WPF i XAML/4 Tworzenie aplikacji WPF.md"
    },
    {
      "basename": "8 Android Components",
      "path": "_ Mobile/Kotlin/the complete Android Kotlin/8 Android Components.md"
    },
    {
      "basename": "8.1 Layouts in Android App",
      "path": "_ Mobile/Kotlin/the complete Android Kotlin/8.1 Layouts in Android App.md"
    },
    {
      "basename": "8.2 TextView",
      "path": "_ Mobile/Kotlin/the complete Android Kotlin/8.2 TextView.md"
    },
    {
      "basename": "8.3 Button",
      "path": "_ Mobile/Kotlin/the complete Android Kotlin/8.3 Button.md"
    },
    {
      "basename": "3 Kotlin fundamentals",
      "path": "_ Mobile/Kotlin/the complete Android 12 and Kotlin/3 Kotlin fundamentals.md"
    },
    {
      "basename": "4. OOP Kotlin",
      "path": "_ Mobile/Kotlin/the complete Android 12 and Kotlin/4. OOP Kotlin.md"
    },
    {
      "basename": "_ C Sharp od Podstaw do WPF i XAML",
      "path": "C Sharp/C Sharp od Podstaw do WPF i XAML/_ C Sharp od Podstaw do WPF i XAML.md"
    },
    {
      "basename": "_ Fast WFP C Sharp",
      "path": "C Sharp/Fast WFP  C Sharp/_ Fast WFP C Sharp.md"
    },
    {
      "basename": "7 Express JS",
      "path": "_ WEB/N_O_D_E/NodeJS - fullstack/7 Express JS.md"
    },
    {
      "basename": "3.1 Express - introducing",
      "path": "_ WEB/N_O_D_E/Mosh Node/3.1 Express - introducing.md"
    },
    {
      "basename": "5 Working with Express.js",
      "path": "_ WEB/N_O_D_E/NODE - the complete guide/5 Working with Express.js.md"
    },
    {
      "basename": "3 Node Basics",
      "path": "_ WEB/N_O_D_E/NODE - the complete guide/3 Node Basics.md"
    },
    {
      "basename": "6 Kotlin OOP",
      "path": "_ Mobile/Kotlin/the complete Android Kotlin/6 Kotlin OOP.md"
    },
    {
      "basename": "ES refresh",
      "path": "JAVASCRIPT/ES refresh.md"
    },
    {
      "basename": "_0 Node Complete Guide",
      "path": "_ WEB/N_O_D_E/NODE - the complete guide/_0 Node Complete Guide.md"
    },
    {
      "basename": "3 Control Flow Statements in Kotlin",
      "path": "_ Mobile/Kotlin/the complete Android Kotlin/3 Control Flow Statements in Kotlin.md"
    },
    {
      "basename": "git",
      "path": "_ WEB/N_O_D_E/Lear Node.js and Javascript/git.md"
    },
    {
      "basename": "docker mysql node phpmyadmin",
      "path": "_ WEB/N_O_D_E/Lear Node.js and Javascript/docker mysql node phpmyadmin.md"
    },
    {
      "basename": "- 5 Stock Market App with Node and JavaScript",
      "path": "_ WEB/N_O_D_E/Lear Node.js and Javascript/- 5 Stock Market App with Node and JavaScript.md"
    },
    {
      "basename": "- 4 MySQL with Node.js",
      "path": "_ WEB/N_O_D_E/Lear Node.js and Javascript/- 4 MySQL with Node.js.md"
    },
    {
      "basename": "_ Node and JavaScript",
      "path": "_ WEB/N_O_D_E/Lear Node.js and Javascript/_ Node and JavaScript.md"
    },
    {
      "basename": "- 3 Node",
      "path": "_ WEB/N_O_D_E/Lear Node.js and Javascript/- 3 Node.md"
    },
    {
      "basename": "- 2 JavaScript",
      "path": "_ WEB/N_O_D_E/Lear Node.js and Javascript/- 2 JavaScript.md"
    },
    {
      "basename": "7 Intro to Android App Development",
      "path": "_ Mobile/Kotlin/the complete Android Kotlin/7 Intro to Android App Development.md"
    },
    {
      "basename": "19 jQuery",
      "path": "_ FullStack/Web Development 2023/19 jQuery.md"
    },
    {
      "basename": "_ 0 start",
      "path": "_ FullStack/Web Development 2023/_ 0 start.md"
    },
    {
      "basename": "Untitled",
      "path": "Untitled.md"
    },
    {
      "basename": "middleware_Draw.excalidraw",
      "path": "Excalidraw/middleware_Draw.excalidraw.md"
    },
    {
      "basename": "Plotly express tworzenie animacji",
      "path": "P Y T H O N/Data Science BootCamp od A do Z 2022/Wizualizacja danych/Plotly express tworzenie animacji.md"
    },
    {
      "basename": "Plotly express mapy",
      "path": "P Y T H O N/Data Science BootCamp od A do Z 2022/Wizualizacja danych/Plotly express mapy.md"
    },
    {
      "basename": "Klasyfikacja binarna - Macierz konfuzji",
      "path": "P Y T H O N/Data Science BootCamp od A do Z 2022/uczenie maszynowe/Klasyfikacja binarna - Macierz konfuzji.md"
    },
    {
      "basename": "Klasyfikacja binarna - ROC",
      "path": "P Y T H O N/Data Science BootCamp od A do Z 2022/uczenie maszynowe/Klasyfikacja binarna - ROC.md"
    },
    {
      "basename": "Pierwszy model",
      "path": "P Y T H O N/Data Science BootCamp od A do Z 2022/uczenie maszynowe/Pierwszy model.md"
    },
    {
      "basename": "przestrzeń probabilistyczna",
      "path": "P Y T H O N/Data Science BootCamp od A do Z 2022/Prawdopodobieństwo i statystyka/przestrzeń probabilistyczna.md"
    },
    {
      "basename": "Odchylenie standardowe",
      "path": "P Y T H O N/Data Science BootCamp od A do Z 2022/Prawdopodobieństwo i statystyka/Odchylenie standardowe.md"
    },
    {
      "basename": "Mediana",
      "path": "P Y T H O N/Data Science BootCamp od A do Z 2022/Prawdopodobieństwo i statystyka/Mediana.md"
    },
    {
      "basename": "Łączenie danych",
      "path": "P Y T H O N/Data Science BootCamp od A do Z 2022/Pandas/Łączenie danych.md"
    },
    {
      "basename": "Filtrowanie danych",
      "path": "P Y T H O N/Data Science BootCamp od A do Z 2022/Pandas/Filtrowanie danych.md"
    },
    {
      "basename": "2-Case Study Google App Store",
      "path": "P Y T H O N/Data Science BootCamp od A do Z 2022/Pandas/2-Case Study Google App Store.md"
    },
    {
      "basename": "NumPy wektory",
      "path": "P Y T H O N/Data Science BootCamp od A do Z 2022/NumPy/NumPy wektory.md"
    },
    {
      "basename": "NumPy typy danych",
      "path": "P Y T H O N/Data Science BootCamp od A do Z 2022/NumPy/NumPy typy danych.md"
    },
    {
      "basename": "NumPy tablice",
      "path": "P Y T H O N/Data Science BootCamp od A do Z 2022/NumPy/NumPy tablice.md"
    },
    {
      "basename": "NumPy indeksowanie wycinanie",
      "path": "P Y T H O N/Data Science BootCamp od A do Z 2022/NumPy/NumPy indeksowanie wycinanie.md"
    },
    {
      "basename": "Numpy liczby pseudolosowe",
      "path": "P Y T H O N/Data Science BootCamp od A do Z 2022/NumPy/Numpy liczby pseudolosowe.md"
    },
    {
      "basename": "Numpy macierze",
      "path": "P Y T H O N/Data Science BootCamp od A do Z 2022/NumPy/Numpy macierze.md"
    },
    {
      "basename": "NumPy funkcje",
      "path": "P Y T H O N/Data Science BootCamp od A do Z 2022/NumPy/NumPy funkcje.md"
    }
  ],
  "omittedPaths": [],
  "maxLength": null,
  "openType": "tab"
}